LICENSE
modularapi/__init__.py
modularapi/app.py
modularapi/asgi.py
modularapi/cli.py
modularapi/db.py
modularapi/settings.py
modularapi/templates/default/alembic.ini.mako
modularapi/templates/default/env.py
modularapi/templates/default/README
modularapi/templates/default/script.py.mako
modularapi/utils.py
modularapi/venv_requirements.txt
modularapi-0.6.1.dist-info/entry_points.txt
modularapi-0.6.1.dist-info/LICENSE
modularapi-0.6.1.dist-info/WHEEL
modularapi-0.6.1.dist-info/METADATA
modularapi-0.6.1.dist-info/RECORD
